keyalias/__init__.py
keyalias/core.py
keyalias/tests/__init__.py
keyalias/tests/test_foo.py
keyalias/tests/test_mock.py
keyalias-1.0.4.dist-info/licenses/LICENSE.txt
keyalias-1.0.4.dist-info/METADATA
keyalias-1.0.4.dist-info/WHEEL
keyalias-1.0.4.dist-info/top_level.txt
keyalias-1.0.4.dist-info/RECORD
