Metadata-Version: 2.4
Name: keyalias
Version: 1.0.4
Summary: This project allows for adding a property that is an alias for an indexer to a class.
Author-email: Johannes <johannes.programming@gmail.com>
License: The MIT License (MIT)
Project-URL: Download, https://pypi.org/project/keyalias/#files
Project-URL: Index, https://pypi.org/project/keyalias/
Project-URL: Source, https://github.com/johannes-programming/keyalias/
Project-URL: Website, https://keyalias.johannes-programming.online/
Classifier: Development Status :: 5 - Production/Stable
Classifier: Intended Audience :: Developers
Classifier: License :: OSI Approved :: MIT License
Classifier: Natural Language :: English
Classifier: Operating System :: OS Independent
Classifier: Programming Language :: Python
Classifier: Programming Language :: Python :: 3
Classifier: Programming Language :: Python :: 3 :: Only
Classifier: Typing :: Typed
Requires-Python: >=3.11
License-File: LICENSE.txt
Dynamic: license-file
